constants.py
qmatrix.py
qmatrix-1.3.1.dist-info/licenses/LICENSE
qmatrix-1.3.1.dist-info/METADATA
qmatrix-1.3.1.dist-info/WHEEL
qmatrix-1.3.1.dist-info/entry_points.txt
qmatrix-1.3.1.dist-info/top_level.txt
qmatrix-1.3.1.dist-info/RECORD
