Metadata-Version: 2.4
Name: qmatrix
Version: 1.3.1
Summary: A high-performance, aesthetically pleasing Matrix rain TUI with horror elements.
Home-page: https://github.com/rexackermann/qmatrix
Author: Rex Ackermann
Author-email: rex@example.com
Classifier: Programming Language :: Python :: 3
Classifier: License :: OSI Approved :: MIT License
Classifier: Operating System :: POSIX :: Linux
License-File: LICENSE
Requires-Dist: requests
Dynamic: author
Dynamic: author-email
Dynamic: classifier
Dynamic: description
Dynamic: description-content-type
Dynamic: home-page
Dynamic: license-file
Dynamic: requires-dist
Dynamic: summary
